eve_sde/__init__.py
eve_sde/admin.py
eve_sde/app_settings.py
eve_sde/apps.py
eve_sde/auth_hooks.py
eve_sde/sde_tasks.py
eve_sde/tasks.py
eve_sde/translation.py
eve_sde/urls.py
eve_sde/views.py
eve_sde/management/__init__.py
eve_sde/management/commands/__init__.py
eve_sde/management/commands/esde_get_all_fields.py
eve_sde/management/commands/esde_load_sde.py
eve_sde/management/commands/esde_load_sde_section.py
eve_sde/management/commands/esde_model_stats.py
eve_sde/managers/__init.py
eve_sde/managers/map.py
eve_sde/migrations/0001_initial.py
eve_sde/migrations/0002_evesdesection.py
eve_sde/migrations/0003_itemtypematerials.py
eve_sde/migrations/0004_rename_release_date_evesde_release_date_and_more.py
eve_sde/migrations/0005_lang_fields.py
eve_sde/migrations/0006_dogmaunit.py
eve_sde/migrations/0007_dogmaattributecategory_dogmaattribute.py
eve_sde/migrations/0008_typedogma.py
eve_sde/migrations/0009_alter_typedogma_item_type.py
eve_sde/migrations/0010_alter_itemtypematerials_item_type.py
eve_sde/migrations/0011_alter_moon_planet_alter_moon_solar_system_and_more.py
eve_sde/migrations/__init__.py
eve_sde/models/__init__.py
eve_sde/models/admin.py
eve_sde/models/base.py
eve_sde/models/map.py
eve_sde/models/types.py
eve_sde/models/utils.py
eve_sde/templates/esde/index.html
eve_sde/tests/__init__.py
eve_sde/tests/test_example.py
django_eveonline_sde-0.0.1a1.dist-info/METADATA
django_eveonline_sde-0.0.1a1.dist-info/WHEEL
django_eveonline_sde-0.0.1a1.dist-info/licenses/LICENSE
django_eveonline_sde-0.0.1a1.dist-info/RECORD
